[
    { "name": "Renee Wong", "date": "1/1/24", "mood_score": 9, "therapist_score": 7, "irritability": 3, "depression": 2, "anxiety": 4, "sleep_quality": 7, "interest_hobbies": 8 },
    { "name": "Renee Wong", "date": "1/2/24", "mood_score": 3, "therapist_score": 7, "irritability": 4, "depression": 3, "anxiety": 5, "sleep_quality": 6, "interest_hobbies": 7 },
    { "name": "Renee Wong", "date": "1/3/24", "mood_score": 7, "therapist_score": 7, "irritability": 3, "depression": 2, "anxiety": 4, "sleep_quality": 7, "interest_hobbies": 8 },
    { "name": "Renee Wong", "date": "1/4/24", "mood_score": 5, "therapist_score": 7, "irritability": 4, "depression": 3, "anxiety": 5, "sleep_quality": 6, "interest_hobbies": 7 },
    { "name": "Renee Wong", "date": "1/5/24", "mood_score": 9, "therapist_score": 7, "irritability": 3, "depression": 2, "anxiety": 4, "sleep_quality": 8, "interest_hobbies": 9 },
    { "name": "Renee Wong", "date": "1/6/24", "mood_score": 4, "therapist_score": 7, "irritability": 5, "depression": 4, "anxiety": 6, "sleep_quality": 5, "interest_hobbies": 6 },
    { "name": "Renee Wong", "date": "1/7/24", "mood_score": 8, "therapist_score": 7, "irritability": 3, "depression": 2, "anxiety": 4, "sleep_quality": 7, "interest_hobbies": 8 },
    
    { "name": "Renee Wong", "date": "1/8/24", "mood_score": 6, "therapist_score": 6, "irritability": 4, "depression": 3, "anxiety": 5, "sleep_quality": 6, "interest_hobbies": 7 },
    { "name": "Renee Wong", "date": "1/9/24", "mood_score": 5, "therapist_score": 6, "irritability": 3, "depression": 2, "anxiety": 4, "sleep_quality": 7, "interest_hobbies": 8 },
    { "name": "Renee Wong", "date": "1/10/24", "mood_score": 8, "therapist_score": 6, "irritability": 4, "depression": 3, "anxiety": 5, "sleep_quality": 6, "interest_hobbies": 7 },
    { "name": "Renee Wong", "date": "1/11/24", "mood_score": 4, "therapist_score": 6, "irritability": 5, "depression": 4, "anxiety": 6, "sleep_quality": 5, "interest_hobbies": 6 },
    { "name": "Renee Wong", "date": "1/12/24", "mood_score": 7, "therapist_score": 6, "irritability": 3, "depression": 2, "anxiety": 4, "sleep_quality": 7, "interest_hobbies": 8 },
    { "name": "Renee Wong", "date": "1/13/24", "mood_score": 6, "therapist_score": 6, "irritability": 4, "depression": 3, "anxiety": 5, "sleep_quality": 6, "interest_hobbies": 7 },
    { "name": "Renee Wong", "date": "1/14/24", "mood_score": 9, "therapist_score": 6, "irritability": 3, "depression": 2, "anxiety": 4, "sleep_quality": 8, "interest_hobbies": 9 },
  
    { "name": "Renee Wong", "date": "1/15/24", "mood_score": 5, "therapist_score": 8, "irritability": 4, "depression": 3, "anxiety": 5, "sleep_quality": 6, "interest_hobbies": 7 },
    { "name": "Renee Wong", "date": "1/16/24", "mood_score": 7, "therapist_score": 8, "irritability": 3, "depression": 2, "anxiety": 4, "sleep_quality": 7, "interest_hobbies": 8 },
    { "name": "Renee Wong", "date": "1/17/24", "mood_score": 8, "therapist_score": 8, "irritability": 4, "depression": 3, "anxiety": 5, "sleep_quality": 6, "interest_hobbies": 7 },
    { "name": "Renee Wong", "date": "1/18/24", "mood_score": 3, "therapist_score": 8, "irritability": 5, "depression": 4, "anxiety": 6, "sleep_quality": 5, "interest_hobbies": 6 },
    { "name": "Renee Wong", "date": "1/19/24", "mood_score": 6, "therapist_score": 8, "irritability": 3, "depression": 2, "anxiety": 4, "sleep_quality": 7, "interest_hobbies": 8 },
    { "name": "Renee Wong", "date": "1/20/24", "mood_score": 9, "therapist_score": 8, "irritability": 4, "depression": 3, "anxiety": 5, "sleep_quality": 6, "interest_hobbies": 7 },
    { "name": "Renee Wong", "date": "1/21/24", "mood_score": 4, "therapist_score": 8, "irritability": 3, "depression": 2, "anxiety": 4, "sleep_quality": 7, "interest_hobbies": 8 },
  
    { "name": "Renee Wong", "date": "1/22/24", "mood_score": 7, "therapist_score": 5, "irritability": 4, "depression": 3, "anxiety": 5, "sleep_quality": 6, "interest_hobbies": 7 },
    { "name": "Renee Wong", "date": "1/23/24", "mood_score": 5, "therapist_score": 5, "irritability": 3, "depression": 2, "anxiety": 4, "sleep_quality": 7, "interest_hobbies": 8 },
    { "name": "Renee Wong", "date": "1/24/24", "mood_score": 8, "therapist_score": 5, "irritability": 4, "depression": 3, "anxiety": 5, "sleep_quality": 6, "interest_hobbies": 7 },
    { "name": "Renee Wong", "date": "1/25/24", "mood_score": 6, "therapist_score": 5, "irritability": 5, "depression": 4, "anxiety": 6, "sleep_quality": 5, "interest_hobbies": 6 }
  ]
  